DESCRIPTION.rst
MANIFEST.in
README.rst
setup.py
assisipy/__init__.py
assisipy/aggregate_data.py
assisipy/assisirun.py
assisipy/bee.py
assisipy/casu.py
assisipy/collect_data.py
assisipy/deploy.py
assisipy/fake_fw.py
assisipy/physical.py
assisipy/sim.py
assisipy.egg-info/PKG-INFO
assisipy.egg-info/SOURCES.txt
assisipy.egg-info/dependency_links.txt
assisipy.egg-info/entry_points.txt
assisipy.egg-info/requires.txt
assisipy.egg-info/top_level.txt
assisipy/msg/__init__.py
assisipy/msg/base_msgs_pb2.py
assisipy/msg/dev_msgs_pb2.py
assisipy/msg/sim_msgs_pb2.py