Metadata-Version: 1.1
Name: assisipy
Version: 0.16.1
Summary: Python API for the ASSISbf project
Home-page: https://github.com/larics/assisi-python
Author: LARICS Laboratory
Author-email: larics@fer.hr
License: LGPL
Keywords: assisi,assisibf,collective systems
Platform: UNKNOWN
Classifier: Development Status :: 5 - Production/Stable
Classifier: Intended Audience :: Developers
Classifier: Topic :: Scientific/Engineering :: Artificial Life
Classifier: License :: OSI Approved :: GNU Library or Lesser General Public License (LGPL)
Classifier: Programming Language :: Python :: 2.7
